quantalogic_markdown_mcp/__init__.py
quantalogic_markdown_mcp/ast_utils.py
quantalogic_markdown_mcp/cli.py
quantalogic_markdown_mcp/enhanced_mcp_server.py
quantalogic_markdown_mcp/mcp_server.py
quantalogic_markdown_mcp/mcp_server_legacy.py
quantalogic_markdown_mcp/parser.py
quantalogic_markdown_mcp/parsers.py
quantalogic_markdown_mcp/renderers.py
quantalogic_markdown_mcp/safe_editor.py
quantalogic_markdown_mcp/safe_editor_types.py
quantalogic_markdown_mcp/stateless_processor.py
quantalogic_markdown_mcp/types.py
quantalogic_markdown_mcp-0.2.2.dist-info/METADATA
quantalogic_markdown_mcp-0.2.2.dist-info/WHEEL
quantalogic_markdown_mcp-0.2.2.dist-info/entry_points.txt
quantalogic_markdown_mcp-0.2.2.dist-info/licenses/LICENSE
quantalogic_markdown_mcp-0.2.2.dist-info/RECORD
