Metadata-Version: 2.4
Name: quantalogic-markdown-mcp
Version: 0.2.2
Summary: A flexible and extensible Markdown parser with AST support
Project-URL: Homepage, https://github.com/raphaelmansuy/quantalogic-markdown-edit-mcp
Project-URL: Repository, https://github.com/raphaelmansuy/quantalogic-markdown-edit-mcp
Project-URL: Documentation, https://github.com/raphaelmansuy/quantalogic-markdown-edit-mcp/docs
Project-URL: Issues, https://github.com/raphaelmansuy/quantalogic-markdown-edit-mcp/issues
Author-email: Raphael Mansuy <raphael.mansuy@gmail.com>
License: MIT
License-File: LICENSE
Keywords: ast,commonmark,markdown,parser
Classifier: Development Status :: 3 - Alpha
Classifier: Intended Audience :: Developers
Classifier: License :: OSI Approved :: MIT License
Classifier: Programming Language :: Python :: 3
Classifier: Programming Language :: Python :: 3.11
Classifier: Programming Language :: Python :: 3.12
Classifier: Topic :: Software Development :: Libraries :: Python Modules
Classifier: Topic :: Text Processing :: Markup
Requires-Python: >=3.11
Requires-Dist: fastmcp>=0.9.0
Requires-Dist: markdown-it-py>=3.0.0
Requires-Dist: mcp[cli]>=1.12.0
Requires-Dist: mdit-py-plugins>=0.4.0
Provides-Extra: dev
Requires-Dist: black>=23.0.0; extra == 'dev'
Requires-Dist: mypy>=1.0.0; extra == 'dev'
Requires-Dist: pytest-cov>=4.0.0; extra == 'dev'
Requires-Dist: pytest>=7.0.0; extra == 'dev'
Requires-Dist: ruff>=0.1.0; extra == 'dev'
Provides-Extra: latex
Requires-Dist: pygments>=2.0.0; extra == 'latex'
Provides-Extra: test
Requires-Dist: pytest-cov>=4.0.0; extra == 'test'
Requires-Dist: pytest>=7.0.0; extra == 'test'
